webblast/blast.py
webblast/utils.py
webblast/web_blast.pl
webblast-0.0.6.dist-info/METADATA
webblast-0.0.6.dist-info/WHEEL
webblast-0.0.6.dist-info/entry_points.txt
webblast-0.0.6.dist-info/RECORD
